MANIFEST.in
README.md
setup.py
signer/__init__.py
signer.egg-info/PKG-INFO
signer.egg-info/SOURCES.txt
signer.egg-info/dependency_links.txt
signer.egg-info/top_level.txt