Metadata-Version: 1.1
Name: signer
Version: 0.0.1
Summary: a python module for message signing
Home-page: https://github.com/zweifisch/signer
Author: Feng Zhou
Author-email: zf.pascal@gmail.com
License: MIT
Keywords: singning
Platform: UNKNOWN
Classifier: Development Status :: 3 - Alpha
Classifier: Operating System :: OS Independent
Classifier: Intended Audience :: Developers
Classifier: License :: OSI Approved :: MIT License
Classifier: Programming Language :: Python :: 3.4
